{"Exif":{"Lat":0,"Long":0,"Date":"2022-06-19T11:16:05-07:00","Tags":{"ApertureValue":4.643856,"BrightnessValue":10.73203125,"CustomRendered|int":"0","DateTimeDigitized|time.Time":"2022-06-19T11:16:05-07:00","DateTimeOriginal|time.Time":"2022-06-19T11:16:05-07:00","DateTime|time.Time":"2022-07-22T18:24:36-07:00","DigitalZoomRatio":1,"ExposureTime|*big.Rat":"1/800","FNumber":5,"FileSource":"","FocalLength":44.6,"FocalLengthIn35mmFilm|int":"44","ISOSpeedRatings|int":"100","LensModel":"24-70mm F2.8 DG DN | Art 019","LightSource|int":"0","Make":"SONY","MaxApertureValue":2.96875,"Model":"ILCE-7M4","SceneCaptureType|int":"0","SceneType":"","ShutterSpeedValue":9.643856,"Software":"Adobe Photoshop Camera Raw 14.2 (Windows)","SubSecTimeDigitized":"106","SubSecTimeOriginal":"106"}}}
